Metadata-Version: 2.1
Name: odoo-addon-hr_employee_service_contract
Version: 18.0.1.0.0.2
Requires-Python: >=3.10
Requires-Dist: odoo-addon-hr_employee_service==18.0.*
Requires-Dist: odoo==18.0.*
Summary: Employee service information & duration based on employee's contracts
Home-page: https://github.com/OCA/hr
License: AGPL-3
Author: CorporateHub, Odoo Community Association (OCA)
Author-email: support@odoo-community.org
Classifier: Programming Language :: Python
Classifier: Framework :: Odoo
Classifier: Framework :: Odoo :: 18.0
Classifier: License :: OSI Approved :: GNU Affero General Public License v3
